<comments xmlns="http://schemas.openxmlformats.org/spreadsheetml/2006/main"><authors><author>Hermes</author></authors><commentList><comment ref="A66" authorId="0" shapeId="0"><text><t xml:space="preserve">【来源】蒋宇飞抖音视频（2026-05-25）"未来5-10年的黄金赛道，深度拆解玻璃基板的万亿机遇"

【信源评估】蒋宇飞⭐⭐⭐高置信度（有产业实操经验，多次验证预测准确）

【逻辑链】
摩尔定律终结→先进封装崛起→玻璃基板替代有机基板
 → 凯盛科技=国内玻璃基板龙头
 → 5-10年赛道，2028年大规模应用

【P值估算】基于单信源（蒋宇飞）→ P≈55%（低于存储赛道的70%+）
→ 信源数量不足，确定性打折

【对持仓影响】🟡 观察仓，优先级低于存储主线

【操作建议】盈亏比2.5:1，AI仓10%（总资金2.5%观察仓）。等回调到¥18-18.5再进。P值待定，需更多信源验证。
</t></text></comment><comment ref="A68" authorId="0" shapeId="0"><text><t>信息源：东方财富+新浪财经2026-06-02
核心数据：
- 银行ETF(512800): 0.796(4/17)→0.761(5/28)→0.790(6/2)，跌幅-1%
- 招商银行: 38.80, 兴业银行: 18.61, 平安银行: 11.08
- 走势：4月中旬以来持续阴跌，5月底略有反弹但未改弱势
新闻：东方财富头条无银行板块专属利好
推理链：去杠杆周期→信贷收缩→银行资产质量承压→板块弱势
P值影响：银行P维持50%（虚P-2pp），无新增正向事件
结论：不建议加仓</t></text></comment><comment ref="A69" authorId="0" shapeId="0"><text><t>信息源：东方财富头条+新浪财经2026-06-02
核心数据：
- 机器人ETF(562500): 1.009(4/17)→1.122(6/2)，涨幅+11%
- 5/7-5/22连续上涨：1.097→1.208，涨幅10%
新闻催化：
- 宇树科技"闪电"过会，73天高效通过审核
- 人形机器人商业化元年将至
- 具身智能迎里程碑时刻
推理链：宇树过会=产业从概念→实质商业化→平安先进制造+永赢先进制造直接受益
P值影响：建议从50%基准上调+8~10pp（产业里程碑事件）
结论：重点关注，强正向信号</t></text></comment><comment ref="A70" authorId="0" shapeId="0"><text><t xml:space="preserve">【来源】群联潘健成(产业高管)+蒋宇飞(6.1两长存储+5.18框架)+宋鸿兵(6.2摩尔定律终结)+周鸿祎(内存决定AI)+用户6.3洞察

【逻辑链】
AI越进化，存储需求指数增长（用户底层范式）
 → 摩尔定律物理+经济双极限→堆叠/先进封装崛起（宋鸿兵+蒋宇飞交叉验证）
 → Flash供给不足，明年更紧张（群联潘健成一线数据）
 → 长鑫+长江国产替代空间6倍（蒋宇飞）
 → 长鑫Q1净利润263亿/长江Q1营收破200亿（业绩验证）
 → 长鑫/长江暂时买不到→买产业链上下游A股标的

【当前状态】🔴最高优先级：P值70%+，5条独立信源同向确认，存储缺货涨价贯穿2026全年

【对持仓影响】
🟢 超级利好：存储赛道 = AI仓位核心（占AI总仓50%）
🟢 利好：澜起科技DDR5接口（存储赛道补充）
🟡 中性：020628芯片ETF不含存储核心成分，不要当存储买

【操作建议】
胜率×赔率：P值70%+（高胜率）× 盈亏比3-4:1（高赔率）= 当前最优AI机会
买入时机：等中期选举年大盘跌15%+或单日暴跌5%+或P值回升55%+
仓位分配：存储选2-3只分散（总资金12.5%），澜起5%，凯盛2.5%观察仓
⚠️ 北京君正年内已+51%，不追高，等回调
</t></text></comment><comment ref="A71" authorId="0" shapeId="0"><text><t xml:space="preserve">【来源】蒋宇飞星光纯叠框架+宋鸿兵华为韬定律+用户"AI瓶颈是内存而非算力"

【逻辑链】
AI算力爆发→内存带宽瓶颈→DDR5渗透率提升
 → 澜起科技=内存接口芯片全球龙头
 → 华为韬(τ)定律：逻辑折叠=超三维堆叠→近存计算→DDR5接口芯片需求暴增
 → 量价齐升，增速50-80%/年

【当前状态】🟡合理估值：PE130x，PEG 1.6-2.6x，¥280以下=合理

【对持仓影响】🟢 存储赛道补充，与存储逻辑互锁

【操作建议】盈亏比4:1，AI仓20%（总资金5%）。等中期选举大跌或P值回升55%+。⚠️股东询价转让(减持利空)需关注。
</t></text></comment><comment ref="A73" authorId="0" shapeId="0"><text><t xml:space="preserve">【标的】北京君正 300223
【核心逻辑】存储+计算芯片，DRAM新工艺突破，车载存储市占率提升。A股年内+51%，市值772亿。港股二度IPO中。盈亏比4:1，存储赛道里最强。

【为什么买】长鑫/长江暂时买不到→买产业链上下游→存储涨价直接受益

【买入条件】等中期选举年大盘跌15%+或单日暴跌5%+或P值回升55%+
【仓位建议】存储选2-3只分散（总资金12.5%），澜起单独5%
【跟踪频率】每日收盘检查价格+每日检查蒋宇飞/群联新观点
</t></text></comment><comment ref="A74" authorId="0" shapeId="0"><text><t xml:space="preserve">【标的】兆易创新 603986
【核心逻辑】NOR Flash国内龙头，DRAM布局中。存储涨价直接受益。盈亏比3.5:1。

【为什么买】长鑫/长江暂时买不到→买产业链上下游→存储涨价直接受益

【买入条件】等中期选举年大盘跌15%+或单日暴跌5%+或P值回升55%+
【仓位建议】存储选2-3只分散（总资金12.5%），澜起单独5%
【跟踪频率】每日收盘检查价格+每日检查蒋宇飞/群联新观点
</t></text></comment></commentList></comments>